setup.py
qb_penTester/__init__.py
qb_penTester.egg-info/PKG-INFO
qb_penTester.egg-info/SOURCES.txt
qb_penTester.egg-info/dependency_links.txt
qb_penTester.egg-info/not-zip-safe
qb_penTester.egg-info/top_level.txt