Metadata-Version: 1.0
Name: qb-penTester
Version: 0.1
Summary: Network penetration tester developed by @kubilayorcun
Home-page: http://github.com/kubilayorcun/qb_penTester
Author: kubilayorcun
Author-email: kubilayorcun5@gmail.com
License: MIT
Platform: UNKNOWN
